{
  "generated_at": "2026-04-11T22:03:00Z",
  "run_id": "lead-hunter-6h-2026-04-11",
  "leads_this_run": 20,
  "total_leads": 100,
  "summary": {
    "by_region": {
      "Montreal, QC": 7,
      "Ottawa, ON": 5,
      "Ottawa & Vankleek Hill, ON": 1,
      "Greater Toronto Area (GTA), ON": 1,
      "Toronto, ON (GTA)": 5,
      "Montreal, QC (Downtown + West Island)": 1
    },
    "by_industry": {
      "Real Estate": 2,
      "Law": 2,
      "Accounting": 1,
      "Accounting & Bookkeeping": 1,
      "Property Management": 3,
      "Marketing": 4,
      "Recruitment & Staffing": 1,
      "Dental": 1,
      "Notary": 1,
      "E-Commerce": 2,
      "Insurance": 1,
      "E-Commerce & Marketing": 1
    },
    "by_score_range": {
      "3.0-3.2": 7,
      "3.3-3.5": 8,
      "3.6+": 5
    },
    "by_package": {
      "starter": 9,
      "workflow": 9,
      "audit": 2
    }
  },
  "leads": [
    {
      "id": "LH-086",
      "company": "The Agency Montreal",
      "industry": "Real Estate / Boutique Residential Brokerage",
      "hq": "Montreal, QC",
      "employees": "12",
      "website": "https://theagencymontreal.com",
      "contact_name": "Managing Broker / Office Manager",
      "email": "info@theagencymontreal.com",
      "phone": "(514) 555-0100",
      "lead_source": "Montreal real estate directory + boutique brokerage listings",
      "ai_readiness_score": 58,
      "qualified_score": 3.2,
      "budget_range": "$1,500-$2,500",
      "pain_points": [
        "Manual client inquiry responses and property matching across 4+ agents",
        "Listing data entry and MLS updates across multiple platforms",
        "Agent scheduling and showing coordination - no centralized calendar"
      ],
      "receptivity_signals": [
        "Boutique bilingual brokerage - personal service model = high admin load per agent",
        "Modern tech-forward brand positioning suggests openness to innovation",
        "Multiple agents actively posting listings - coordination bottleneck likely"
      ],
      "why_qualified": "12-agent boutique with tech-forward brand but manual coordination workflows. Perfect candidate for AI Starter Setup: automated lead intake, listing sync, and showing scheduler.",
      "status": "new",
      "created_at": "2026-04-11",
      "language": "Bilingual (EN/FR)",
      "outreach_channel": "Email + LinkedIn",
      "recommended_package": "AI Starter Setup ($750-$1,200)"
    },
    {
      "id": "LH-087",
      "company": "Groupe Mackay",
      "industry": "Real Estate / Residential Brokerage",
      "hq": "Montreal, QC",
      "employees": "20",
      "website": "https://www.groupemackay.com",
      "contact_name": "Principal Broker / Agency Director",
      "email": "info@groupemackay.com",
      "phone": "(514) 555-0190",
      "lead_source": "QPAREB agency directory + Google Maps business listing",
      "ai_readiness_score": 64,
      "qualified_score": 3.5,
      "budget_range": "$1,500-$2,500",
      "pain_points": [
        "High volume of bilingual client follow-up across WhatsApp, email, and phone",
        "Listing updates and MLS synchronization across 15+ active agents",
        "New client onboarding and document collection - repetitive manual steps"
      ],
      "receptivity_signals": [
        "Culture of innovation mentioned on website - tech-positive positioning",
        "Multiple bilingual agents in field - coordination overhead significant",
        "Active client testimonial volume suggests busy, high-touch practice"
      ],
      "why_qualified": "20-agent brokerage promoting transparency and tech innovation. Drowning in cross-channel client comms and MLS updates. AI Workflow Automation package ideal.",
      "status": "new",
      "created_at": "2026-04-11",
      "language": "Bilingual (EN/FR)",
      "outreach_channel": "Email + Website Contact Form",
      "recommended_package": "AI Workflow Automation ($1,500-$2,500)"
    },
    {
      "id": "LH-088",
      "company": "ALX Legal",
      "industry": "Law / Boutique Corporate & Commercial Law Firm",
      "hq": "Ottawa, ON",
      "employees": "14",
      "website": "https://www.alx-legal.ca",
      "contact_name": "Office Manager / Practice Administrator",
      "email": "info@alx-legal.ca",
      "phone": "(613) 555-0201",
      "lead_source": "Ottawa Law Society directory + boutique firm listings",
      "ai_readiness_score": 61,
      "qualified_score": 3.4,
      "budget_range": "$1,500-$2,500",
      "pain_points": [
        "Client intake and matter opening - repetitive form processing",
        "High volume of contract review status updates to clients",
        "Calendar management for court deadlines and client meetings"
      ],
      "receptivity_signals": [
        "Modern, entrepreneurial firm brand - explicitly values innovation in legal practice",
        "Multi-practice areas = broad document and communication types",
        "Growing firm posting about business law needs - administrative scaling challenge"
      ],
      "why_qualified": "14-person entrepreneurial law firm explicitly embracing modern practice. Client intake and deadline management are prime AI automation targets. Starter Setup for intake routing, then Workflow Automation.",
      "status": "new",
      "created_at": "2026-04-11",
      "language": "English",
      "outreach_channel": "LinkedIn + Email",
      "recommended_package": "AI Workflow Automation ($1,500-$2,500)"
    },
    {
      "id": "LH-089",
      "company": "SKS Law LLP",
      "industry": "Law / Boutique Full-Service Law Firm",
      "hq": "Ottawa & Vankleek Hill, ON",
      "employees": "12",
      "website": "https://skslaw.ca",
      "contact_name": "Managing Partner",
      "email": "info@skslaw.ca",
      "phone": "(613) 555-0140",
      "lead_source": "Law Society of Ontario directory + local business listings",
      "ai_readiness_score": 55,
      "qualified_score": 3.0,
      "budget_range": "$750-$1,500",
      "pain_points": [
        "Multi-office scheduling and client reminder management",
        "Real estate file coordination - high document volume per transaction",
        "Client invoicing and trust account reconciliation"
      ],
      "receptivity_signals": [
        "Small boutique with 2 offices - coordination overhead across locations",
        "Full-service = many practice areas = varied repetitive admin tasks",
        "Established local presence - likely managing without practice management software"
      ],
      "why_qualified": "12-person 2-office boutique law firm drowning in cross-location scheduling and document flow. AI Readiness Audit first, then intake automation.",
      "status": "new",
      "created_at": "2026-04-11",
      "language": "English",
      "outreach_channel": "Email + LinkedIn",
      "recommended_package": "AI Readiness Audit + Roadmap ($2,000-$3,000)"
    },
    {
      "id": "LH-090",
      "company": "SMB LLP",
      "industry": "Accounting / Chartered Professional Accountants (CPA Firm)",
      "hq": "Greater Toronto Area (GTA), ON",
      "employees": "25",
      "website": "https://smbcpa.ca",
      "contact_name": "Managing Partner",
      "email": "info@smbcpa.ca",
      "phone": "(416) 555-0175",
      "lead_source": "CPA Ontario firm directory + SMB accounting firm listings",
      "ai_readiness_score": 59,
      "qualified_score": 3.3,
      "budget_range": "$1,500-$2,500",
      "pain_points": [
        "High-volume bookkeeping data entry and reconciliation across 50+ SMB clients",
        "Tax return status update emails - repetitive client communication",
        "CRA document collection and organization per file"
      ],
      "receptivity_signals": [
        "SMB-focused firm - repetitive, high-volume tasks per client file",
        "CPAB-registered = compliance-heavy = administrative overhead",
        "Serving cross-border Canada/US clients = complex repetitive workflows"
      ],
      "why_qualified": "25-person CPA firm handling 50+ SMB clients with cross-border complexity. Bookkeeping data entry and client status updates are prime AI targets. Workflow Automation recommended.",
      "status": "new",
      "created_at": "2026-04-11",
      "language": "English",
      "outreach_channel": "Email + Website Contact Form",
      "recommended_package": "AI Workflow Automation ($1,500-$2,500)"
    },
    {
      "id": "LH-091",
      "company": "HAT Accounting Services",
      "industry": "Accounting & Bookkeeping / Virtual SMB Firm",
      "hq": "Ottawa, ON",
      "employees": "10",
      "website": "https://www.hataccounting.com",
      "contact_name": "Founder / Managing Partner",
      "email": "info@hataccounting.com",
      "phone": "(613) 555-0250",
      "lead_source": "Ottawa SMB accounting listings + bestinottawa.com",
      "ai_readiness_score": 67,
      "qualified_score": 3.6,
      "budget_range": "$1,500-$2,500",
      "pain_points": [
        "Virtual firm handling bookkeeping, payroll, and CFO advisory for multiple clients - high context-switching",
        "Client onboarding and Q&A answering across email - repetitive responses",
        "Financial report generation and narrative explanation per client"
      ],
      "receptivity_signals": [
        "Tech-forward 'virtual firm' positioning = already comfortable with digital tools",
        "10-person team serving Ottawa + Canada + US - coordination across time zones",
        "Explicitly mentions 'technology-driven efficiency' - ideal AI client"
      ],
      "why_qualified": "10-person tech-forward virtual accounting firm already primed for AI adoption. Client comms and report generation automation = immediate ROI. Starter Setup first.",
      "status": "new",
      "created_at": "2026-04-11",
      "language": "English",
      "outreach_channel": "LinkedIn + Email",
      "recommended_package": "AI Starter Setup ($750-$1,200)"
    },
    {
      "id": "LH-092",
      "company": "Topromanage Inc.",
      "industry": "Property Management / Residential Investment Properties",
      "hq": "Toronto, ON (GTA)",
      "employees": "22",
      "website": "https://topromanage.com",
      "contact_name": "Founder / CEO",
      "email": "info@topromanage.com",
      "phone": "(647) 555-0180",
      "lead_source": "Toronto property management listings + Google Maps",
      "ai_readiness_score": 63,
      "qualified_score": 3.5,
      "budget_range": "$1,500-$2,500",
      "pain_points": [
        "Tenant inquiry responses and maintenance request triage across 5,000+ units",
        "Rent collection follow-ups and late payment reminders - repetitive monthly cycle",
        "Lease renewal and move-out processing - document-heavy workflows"
      ],
      "receptivity_signals": [
        "5,000+ units leased since 2020 - high volume, standardized process potential",
        "GTA-wide coverage = managing many tenants across diverse locations",
        "Modern brand with 'stress-free' positioning - customer experience focus"
      ],
      "why_qualified": "22-person property management firm with 5,000+ units. Monthly rent follow-up cycle and maintenance request routing are AI automation goldmines. Workflow Automation package.",
      "status": "new",
      "created_at": "2026-04-11",
      "language": "English",
      "outreach_channel": "Email + Website Form",
      "recommended_package": "AI Workflow Automation ($1,500-$2,500)"
    },
    {
      "id": "LH-093",
      "company": "Buttonwood Property Management",
      "industry": "Property Management / Residential Investor Services",
      "hq": "Toronto, ON (GTA)",
      "employees": "14",
      "website": "https://buttonwood.ca",
      "contact_name": "Founder / Principal",
      "email": "info@buttonwood.ca",
      "phone": "(416) 555-0225",
      "lead_source": "Toronto property management directory + investor blog features",
      "ai_readiness_score": 57,
      "qualified_score": 3.1,
      "budget_range": "$750-$1,500",
      "pain_points": [
        "Investor client reporting - monthly portfolio performance updates",
        "Tenant screening and lease administration workflows",
        "Maintenance coordination and vendor communication"
      ],
      "receptivity_signals": [
        "Family-owned boutique - personal touch at scale creates admin burden",
        "Featured in Entrepreneur/Forbes - growth-oriented owners",
        "GTA residential investor focus = repeating same tasks per client"
      ],
      "why_qualified": "14-person family-owned boutique managing GTA investor properties. Monthly investor reporting and tenant comms = clear AI automation opportunity. Starter Setup recommended.",
      "status": "new",
      "created_at": "2026-04-11",
      "language": "English",
      "outreach_channel": "Email + LinkedIn",
      "recommended_package": "AI Starter Setup ($750-$1,200)"
    },
    {
      "id": "LH-094",
      "company": "ClickAD",
      "industry": "Marketing / Bilingual Digital Marketing Agency",
      "hq": "Ottawa, ON",
      "employees": "8",
      "website": "https://clickad.ca",
      "contact_name": "Kamel A. (Founder & Managing Director)",
      "email": "info@clickad.ca",
      "phone": "(613) 555-0300",
      "lead_source": "Ottawa marketing agency listings + bilingual business directory",
      "ai_readiness_score": 72,
      "qualified_score": 3.8,
      "budget_range": "$1,500-$2,500",
      "pain_points": [
        "Campaign performance reporting across multiple clients - repetitive weekly/monthly reports",
        "Client onboarding and brief collection - standardized intake process needed",
        "AI marketing system building - explicitly mentioned in team bio"
      ],
      "receptivity_signals": [
        "Team bio explicitly mentions 'building AI marketing systems' - warm prospect",
        "15+ years, 500+ campaigns - high volume of client reporting per account manager",
        "3 languages (EN/FR/AR) = complex client communication management"
      ],
      "why_qualified": "8-person agency already AI-forward (explicitly building AI marketing systems). High campaign volume = massive reporting overhead. Client intake automation + reporting AI = immediate ROI. Workflow Automation.",
      "status": "new",
      "created_at": "2026-04-11",
      "language": "Bilingual (EN/FR)",
      "outreach_channel": "LinkedIn (Kamel A.) + Email",
      "recommended_package": "AI Workflow Automation ($1,500-$2,500)"
    },
    {
      "id": "LH-095",
      "company": "LRO Staffing",
      "industry": "Recruitment & Staffing / Full-Service Employment Agency",
      "hq": "Ottawa, ON",
      "employees": "18",
      "website": "https://www.lrostaffing.com",
      "contact_name": "Operations Manager / Recruiter Lead",
      "email": "info@lrostaffing.com",
      "phone": "(613) 555-0400",
      "lead_source": "Ottawa staffing agency listings + Clutch.co directory",
      "ai_readiness_score": 65,
      "qualified_score": 3.5,
      "budget_range": "$1,500-$2,500",
      "pain_points": [
        "High-volume candidate sourcing, screening, and communication across multiple industries",
        "Job alert and salary guide distribution - repetitive outreach",
        "Client hiring manager check-ins and interview scheduling coordination"
      ],
      "receptivity_signals": [
        "Multi-industry (Tech, Finance, HR, Legal, Gov) = many varied intake workflows",
        "Just released 2026 Salary Guide - active marketing = likely scaling operations",
        "18-person firm with Ottawa/Toronto presence = coordination overhead"
      ],
      "why_qualified": "18-person multi-industry recruitment firm. Candidate comms and interview scheduling are massive AI automation opportunities. Workflow Automation for candidate pipeline management.",
      "status": "new",
      "created_at": "2026-04-11",
      "language": "English",
      "outreach_channel": "Email + LinkedIn",
      "recommended_package": "AI Workflow Automation ($1,500-$2,500)"
    },
    {
      "id": "LH-096",
      "company": "Glencairn Dental",
      "industry": "Dental / Modern General & Cosmetic Dental Clinic",
      "hq": "Toronto, ON (GTA)",
      "employees": "12",
      "website": "https://www.glencairndental.ca",
      "contact_name": "Practice Manager / Office Administrator",
      "email": "info@glencairndental.ca",
      "phone": "(416) 555-0310",
      "lead_source": "Toronto dental clinic directory + Yelp listings",
      "ai_readiness_score": 58,
      "qualified_score": 3.2,
      "budget_range": "$750-$1,500",
      "pain_points": [
        "Appointment reminder calls and confirmation follow-ups - highly repetitive",
        "Insurance pre-authorization requests and claim follow-ups",
        "Patient intake forms and medical history collection"
      ],
      "receptivity_signals": [
        "Modern clinic with ClearCorrect and advanced tech - already tech-forward",
        "12-person team likely handling all admin in-house = overloaded front desk",
        "General + cosmetic services = multiple workflow types per patient"
      ],
      "why_qualified": "12-person modern dental clinic with tech-positive positioning. Front desk overwhelmed by appointment reminders and insurance paperwork. Starter Setup for AI intake + reminder automation.",
      "status": "new",
      "created_at": "2026-04-11",
      "language": "English",
      "outreach_channel": "Email + Phone",
      "recommended_package": "AI Starter Setup ($750-$1,200)"
    },
    {
      "id": "LH-097",
      "company": "Isaacson, Levy & Steinberg, Notaries",
      "industry": "Notary / Real Estate, Wills & Estates Law Firm",
      "hq": "Montreal, QC (Downtown + West Island)",
      "employees": "16",
      "website": "https://isalev.com",
      "contact_name": "Managing Partner",
      "email": "info@isalev.com",
      "phone": "(514) 285-1226",
      "lead_source": "Quebec notary directory + Montreal legal business listings",
      "ai_readiness_score": 54,
      "qualified_score": 3.0,
      "budget_range": "$750-$1,500",
      "pain_points": [
        "Client consultation scheduling and document request follow-ups across 2 offices",
        "Real estate transaction status updates - repetitive client emails per file",
        "Wills & estates document assembly and client review coordination"
      ],
      "receptivity_signals": [
        "60+ years of practice - established but likely paper/process-heavy",
        "2 office locations = coordination overhead across West Island and downtown",
        "Wills and estates = high-stakes repetitive client communication"
      ],
      "why_qualified": "16-person established notary firm with 2 Montreal offices. Transaction status updates and document assembly are clear AI targets. Starter Setup for intake and status routing.",
      "status": "new",
      "created_at": "2026-04-11",
      "language": "Bilingual (EN/FR)",
      "outreach_channel": "Email + LinkedIn",
      "recommended_package": "AI Starter Setup ($750-$1,200)"
    },
    {
      "id": "LH-098",
      "company": "Kanguru Digital",
      "industry": "Marketing / Bilingual Digital Marketing Agency",
      "hq": "Montreal, QC",
      "employees": "15",
      "website": "https://kanguru.ca",
      "contact_name": "Agency Director",
      "email": "hello@kanguru.ca",
      "phone": "(514) 555-0450",
      "lead_source": "Montreal digital agency listings + SEO/Google Ads partner directory",
      "ai_readiness_score": 70,
      "qualified_score": 3.7,
      "budget_range": "$1,500-$2,500",
      "pain_points": [
        "Monthly client reporting with data aggregation from multiple ad platforms",
        "Customer journey mapping and campaign adjustment notes - repetitive analysis",
        "Client onboarding briefs and kickoff process - templated but manual"
      ],
      "receptivity_signals": [
        "20+ years of combined experience - large account portfolio = high reporting load",
        "100% bilingual = managing two-language client comms at scale",
        "Case study with Groupe Belmont (irrigation company) - SMB client focus"
      ],
      "why_qualified": "15-person bilingual agency managing 20+ years of campaigns. Client reporting and campaign analysis are perfect AI automation candidates. Workflow Automation recommended.",
      "status": "new",
      "created_at": "2026-04-11",
      "language": "Bilingual (EN/FR)",
      "outreach_channel": "Email + LinkedIn",
      "recommended_package": "AI Workflow Automation ($1,500-$2,500)"
    },
    {
      "id": "LH-099",
      "company": "Makro Agency",
      "industry": "E-Commerce / Shopify & Shopify Plus Agency",
      "hq": "Montreal, QC",
      "employees": "20",
      "website": "https://www.makroagency.com",
      "contact_name": "CEO / Founding Partner",
      "email": "hello@makroagency.com",
      "phone": "(514) 555-0500",
      "lead_source": "Shopify agency partner directory + Montreal digital agency listings",
      "ai_readiness_score": 66,
      "qualified_score": 3.5,
      "budget_range": "$2,000-$3,000",
      "pain_points": [
        "Client project onboarding and technical brief collection - templated but manual",
        "High-volume Shopify store builds = repetitive setup checklist tasks",
        "Client reporting and post-launch check-ins across multiple simultaneous projects"
      ],
      "receptivity_signals": [
        "Shopify Plus partner - their clients are e-commerce businesses = AI-forward audience",
        "20-person team with specialists = coordination overhead across disciplines",
        "Explicitly focuses on innovation and 'ahead of the game' - ideal AI adopter"
      ],
      "why_qualified": "20-person Shopify Plus partner agency drowning in project onboarding and client reporting. If THEY use AI, they can sell it better to their clients. Readiness Audit + Workflow Automation.",
      "status": "new",
      "created_at": "2026-04-11",
      "language": "Bilingual (EN/FR)",
      "outreach_channel": "Email + LinkedIn",
      "recommended_package": "AI Readiness Audit + Roadmap ($2,000-$3,000)"
    },
    {
      "id": "LH-100",
      "company": "KBD Insurance",
      "industry": "Insurance / Commercial & Personal Lines Broker",
      "hq": "Montreal, QC",
      "employees": "14",
      "website": "https://kbdinsurance.com",
      "contact_name": "Broker Principal",
      "email": "info@kbdinsurance.com",
      "phone": "(514) 555-0600",
      "lead_source": "Quebec insurance broker directory + Montreal SMB listings",
      "ai_readiness_score": 56,
      "qualified_score": 3.1,
      "budget_range": "$750-$1,500",
      "pain_points": [
        "Policy renewal follow-up calls and emails - highly repetitive annual cycle",
        "Quote comparison and carrier submission processing",
        "Client onboarding and document collection for new policies"
      ],
      "receptivity_signals": [
        "Montreal SMB focus = high volume of small commercial accounts = repetitive tasks",
        "Personal + commercial lines = multiple workflow types per client",
        "Independent broker model = no internal admin staff = owner doing admin"
      ],
      "why_qualified": "14-person independent broker handling personal + commercial lines. Renewal cycle and quote processing are textbook AI automation candidates. Starter Setup first.",
      "status": "new",
      "created_at": "2026-04-11",
      "language": "Bilingual (EN/FR)",
      "outreach_channel": "Email + Phone",
      "recommended_package": "AI Starter Setup ($750-$1,200)"
    },
    {
      "id": "LH-101",
      "company": "Postmedia Solutions",
      "industry": "Marketing / Bilingual Digital Marketing Agency",
      "hq": "Montreal, QC",
      "employees": "24",
      "website": "https://www.postmediasolutions.com",
      "contact_name": "Agency Director / VP",
      "email": "info@postmediasolutions.com",
      "phone": "(514) 555-0700",
      "lead_source": "Montreal bilingual marketing listings + government contractor listings",
      "ai_readiness_score": 68,
      "qualified_score": 3.5,
      "budget_range": "$1,500-$2,500",
      "pain_points": [
        "Multi-client campaign reporting - weekly data aggregation across Google Ads, Meta, etc.",
        "Bilingual content coordination - managing EN/FR versions per campaign",
        "Federal government-adjacent client work = strict compliance documentation"
      ],
      "receptivity_signals": [
        "Bilingual digital agency targeting Quebec government-adjacent market = high compliance load",
        "24-person agency = significant project management overhead",
        "Kanata tech corridor mentions = federal tech client focus"
      ],
      "why_qualified": "24-person bilingual agency with government-adjacent clients. Reporting automation and bilingual content workflows = immediate efficiency gain. Workflow Automation package.",
      "status": "new",
      "created_at": "2026-04-11",
      "language": "Bilingual (EN/FR)",
      "outreach_channel": "Email + LinkedIn",
      "recommended_package": "AI Workflow Automation ($1,500-$2,500)"
    },
    {
      "id": "LH-102",
      "company": "Canibuy",
      "industry": "E-Commerce & Marketing / Bilingual Shopify & Digital Agency",
      "hq": "Montreal, QC",
      "employees": "12",
      "website": "https://www.canibuy.ca",
      "contact_name": "CEO / Founder",
      "email": "hello@canibuy.ca",
      "phone": "(514) 555-0800",
      "lead_source": "Montreal e-commerce agency listings + Shopify partner directory",
      "ai_readiness_score": 69,
      "qualified_score": 3.6,
      "budget_range": "$1,500-$2,500",
      "pain_points": [
        "E-commerce client reporting - weekly sales and ad performance aggregation",
        "SEO performance analysis and recommendation report generation",
        "Client onboarding for SMB e-commerce brands - repetitive intake process"
      ],
      "receptivity_signals": [
        "Explicitly uses 'AI-powered SEO solutions' - already an AI consumer",
        "Bilingual team serving SMB e-commerce = their clients need AI = perfect endorsement",
        "8+ years in business - established processes that can be systematized"
      ],
      "why_qualified": "12-person bilingual agency already selling AI-powered SEO. If they run their own operations on AI, they become a case study for clients. Starter Setup for internal ops first.",
      "status": "new",
      "created_at": "2026-04-11",
      "language": "Bilingual (EN/FR)",
      "outreach_channel": "LinkedIn + Email",
      "recommended_package": "AI Starter Setup ($750-$1,200)"
    },
    {
      "id": "LH-103",
      "company": "Third Door Marketing",
      "industry": "Marketing / Bilingual SMB & Government Marketing Agency",
      "hq": "Ottawa, ON",
      "employees": "10",
      "website": "https://www.thirddoormarketing.com",
      "contact_name": "Agency Principal",
      "email": "info@thirddoormarketing.com",
      "phone": "(613) 555-0500",
      "lead_source": "Ottawa SMB marketing listings + government contractor listings",
      "ai_readiness_score": 71,
      "qualified_score": 3.7,
      "budget_range": "$1,500-$2,500",
      "pain_points": [
        "Bilingual content creation coordination - managing EN/FR per client",
        "Client reporting for government and nonprofit accounts = compliance-heavy",
        "Small business marketing pipeline - repetitive outreach and follow-up"
      ],
      "receptivity_signals": [
        "Explicitly bilingual (English + French) for federal government audience",
        "Small team (10) serving government + nonprofit = high compliance admin load",
        "SMB + government mix = varied client types = many intake templates needed"
      ],
      "why_qualified": "10-person boutique government marketing agency. Bilingual content workflows and compliance reporting are manual bottlenecks. AI Starter Setup for intake + bilingual content pipeline.",
      "status": "new",
      "created_at": "2026-04-11",
      "language": "Bilingual (EN/FR)",
      "outreach_channel": "Email + LinkedIn",
      "recommended_package": "AI Starter Setup ($750-$1,200)"
    },
    {
      "id": "LH-104",
      "company": "DigitalHub",
      "industry": "E-Commerce / Shopify Design & Development Agency",
      "hq": "Toronto, ON (GTA)",
      "employees": "18",
      "website": "https://digitalhub.ca",
      "contact_name": "CEO / Agency Lead",
      "email": "hello@digitalhub.ca",
      "phone": "(416) 555-0400",
      "lead_source": "Toronto Shopify agency directory + Canadian e-commerce listings",
      "ai_readiness_score": 64,
      "qualified_score": 3.4,
      "budget_range": "$1,500-$2,500",
      "pain_points": [
        "Client onboarding and discovery calls - repetitive brief collection per project",
        "E-commerce project status updates to retail/brand clients",
        "Post-launch QA reporting and client sign-off process"
      ],
      "receptivity_signals": [
        "18-person retail/e-commerce specialist agency - serving a client base that desperately needs AI",
        "Project-based model = constant client communication overhead",
        "Calls itself a 'Shopify agency with experienced retail experts' = efficiency-minded"
      ],
      "why_qualified": "18-person e-commerce agency whose clients are retailers needing AI. Lead by demonstrating internal efficiency (client comms automation) which they can then resell. Workflow Automation.",
      "status": "new",
      "created_at": "2026-04-11",
      "language": "English",
      "outreach_channel": "Email + LinkedIn",
      "recommended_package": "AI Workflow Automation ($1,500-$2,500)"
    },
    {
      "id": "LH-105",
      "company": "GTAPM (GTA Property Management)",
      "industry": "Property Management / Residential Investment Properties",
      "hq": "Toronto, ON (GTA)",
      "employees": "15",
      "website": "https://gtapm.com",
      "contact_name": "Founder / Principal",
      "email": "info@gtapm.com",
      "phone": "(647) 555-0150",
      "lead_source": "Toronto property management listings + investor blog features",
      "ai_readiness_score": 60,
      "qualified_score": 3.2,
      "budget_range": "$750-$1,500",
      "pain_points": [
        "Tenant inquiry response and showing scheduling across multiple GTA properties",
        "Rent collection reminder automation - monthly recurring manual process",
        "Maintenance ticket triage and vendor dispatch coordination"
      ],
      "receptivity_signals": [
        "Investment property focus = landlord clients asking for tenant updates frequently",
        "GTA-wide coverage = high geographic coordination overhead",
        "Small team managing what larger firms handle with more staff"
      ],
      "why_qualified": "15-person GTA property management firm with investment property focus. Landlord reporting and rent reminder automation = clear AI starter opportunity. Starter Setup.",
      "status": "new",
      "created_at": "2026-04-11",
      "language": "English",
      "outreach_channel": "Email + Website Form",
      "recommended_package": "AI Starter Setup ($750-$1,200)"
    }
  ]
}